keragan/GAN.py
keragan/GANTrainer.py
keragan/ImageDataset.py
keragan/__init__.py
keragan/trainer.py
keragan/utils.py
keragan-0.0.1.dist-info/METADATA
keragan-0.0.1.dist-info/WHEEL
keragan-0.0.1.dist-info/top_level.txt
keragan-0.0.1.dist-info/RECORD
